COPYING.md
pycirkuit/__init__.py
pycirkuit/exceptions.py
pycirkuit/highlighter.py
pycirkuit/imageviewer.py
pycirkuit/main.py
pycirkuit/texteditor.py
pycirkuit/doc/llista_macros_darrow.txt
pycirkuit/doc/llista_macros_lib3D.txt
pycirkuit/doc/llista_macros_libcct.txt
pycirkuit/doc/llista_macros_libgen.txt
pycirkuit/doc/llista_macros_liblog.txt
pycirkuit/doc/process.ckt
pycirkuit/doc/process.tikz
pycirkuit/examples/2-stage filter.ckt
pycirkuit/examples/CE-BJT amplifier in DC.ckt
pycirkuit/examples/CE-BJT amplifier model (HF).ckt
pycirkuit/examples/Electro-mechanical system.ckt
pycirkuit/examples/LPF - noninverting.ckt
pycirkuit/examples/Laplace transformed circuit.ckt
pycirkuit/examples/Motor-relay.ckt
pycirkuit/examples/Multiple-FeedBack.ckt
pycirkuit/examples/Sallen-Key.ckt
pycirkuit/examples/Signal_conditioner.ckt
pycirkuit/examples/Timer-solution.ckt
pycirkuit/lib/README
pycirkuit/resources/__init__.py
pycirkuit/resources/resources_rc.py
pycirkuit/templates/cm_tikz.tpl
pycirkuit/tools/__init__.py
pycirkuit/tools/circuitmacrosmanager.py
pycirkuit/tools/cliparser.py
pycirkuit/tools/dpic.py
pycirkuit/tools/m4.py
pycirkuit/tools/pdflatex.py
pycirkuit/tools/pdftojpg.py
pycirkuit/tools/pdftopng.py
pycirkuit/tools/processor.py
pycirkuit/tools/tool_base.py
pycirkuit/ui/Ui_aboutdialog.py
pycirkuit/ui/Ui_configdialog.py
pycirkuit/ui/Ui_mainwindow.py
pycirkuit/ui/__init__.py
pycirkuit/ui/aboutdialog.py
pycirkuit/ui/configdialog.py
pycirkuit/ui/mainwindow.py
pycirkuit-0.5.1.dist-info/COPYING.md
pycirkuit-0.5.1.dist-info/METADATA
pycirkuit-0.5.1.dist-info/WHEEL
pycirkuit-0.5.1.dist-info/entry_points.txt
pycirkuit-0.5.1.dist-info/top_level.txt
pycirkuit-0.5.1.dist-info/zip-safe
pycirkuit-0.5.1.dist-info/RECORD
