Metadata-Version: 2.1
Name: pycirkuit
Version: 0.5.1
Summary: A front-end for Circuit Macros
Home-page: https://github.com/orestesmas/pycirkuit
Author: Orestes Mas
Author-email: orestes@tsc.upc.edu
License: GPLv3+
Platform: UNKNOWN
Classifier: Programming Language :: Python :: 3
Classifier: License :: OSI Approved :: GNU General Public License v3 or later (GPLv3+)
Classifier: Operating System :: OS Independent
Classifier: Topic :: Multimedia :: Graphics :: Editors
Classifier: Topic :: Scientific/Engineering
Classifier: Intended Audience :: Education
Classifier: Intended Audience :: Science/Research
Classifier: Intended Audience :: End Users/Desktop
Requires-Dist: PyQt5
Requires-Dist: wheel
Requires-Dist: python-magic
